README.md
setup.py
bftool/__init__.py
bftool/__main__.py
bftool/arguments.py
bftool/bftool_pool.py
bftool/bftool_types.py
bftool/bruteforce.py
bftool/code_import.py
bftool/file_reading.py
bftool_pkg_sulcud.egg-info/PKG-INFO
bftool_pkg_sulcud.egg-info/SOURCES.txt
bftool_pkg_sulcud.egg-info/dependency_links.txt
bftool_pkg_sulcud.egg-info/top_level.txt