Metadata-Version: 2.1
Name: bftool-pkg-sulcud
Version: 2.0.1
Summary: A python module and script to execute functions inside a custom pool that distribute workers between threads and processes
Home-page: https://github.com/shoriwe/bftool
Author: Antonio Donis
Author-email: antoniojosedonishung@gmail.com
License: UNKNOWN
Platform: UNKNOWN
Classifier: Programming Language :: Python :: 3
Classifier: License :: OSI Approved :: MIT License
Classifier: Operating System :: OS Independent
Requires-Python: >=3.6
